setup.py
bin/pipecat-charger-status
bin/pipecat-wind-status
pipecat/__init__.py
pipecat/compatibility.py
pipecat/connect.py
pipecat/filter.py
pipecat/http.py
pipecat/limit.py
pipecat/queue.py
pipecat/record.py
pipecat/test.py
pipecat/udp.py
pipecat/utility.py
pipecat/xml.py
pipecat.egg-info/PKG-INFO
pipecat.egg-info/SOURCES.txt
pipecat.egg-info/dependency_links.txt
pipecat.egg-info/requires.txt
pipecat.egg-info/top_level.txt
pipecat/device/__init__.py
pipecat/device/auto.py
pipecat/device/charger.py
pipecat/device/clock.py
pipecat/device/gps.py
pipecat/device/motion.py
pipecat/device/serial.py
pipecat/device/weather.py
pipecat/store/__init__.py
pipecat/store/csv.py
pipecat/store/pickle.py