Metadata-Version: 1.1
Name: pipecat
Version: 0.3.0
Summary: Elegant, flexible data logging in Python for connected sensors and instruments.
Home-page: http://pipecat.readthedocs.org
Author: Timothy M. Shead
Author-email: tim@shead-custom-design.gov
License: UNKNOWN
Platform: UNKNOWN
Classifier: Development Status :: 3 - Alpha
Classifier: Intended Audience :: Developers
Classifier: Intended Audience :: Education
Classifier: Intended Audience :: Information Technology
Classifier: Intended Audience :: Science/Research
Classifier: License :: OSI Approved :: GNU General Public License v3 or later (GPLv3+)
Classifier: Natural Language :: English
Classifier: Programming Language :: Python :: 2
Classifier: Programming Language :: Python :: 3
Classifier: Topic :: Communications
Classifier: Topic :: Scientific/Engineering
Classifier: Topic :: Utilities
